hgcroc_configuration_client/client.py
hgcroc_configuration_client/tests.py
hgcroc_configuration_client/zmq_compatibility_layer.py
hgcroc_configuration_client/zmq_controler.py
hgcroc_configuration_client-1.2.3.dist-info/METADATA
hgcroc_configuration_client-1.2.3.dist-info/WHEEL
hgcroc_configuration_client-1.2.3.dist-info/top_level.txt
hgcroc_configuration_client-1.2.3.dist-info/RECORD
