Metadata-Version: 2.1
Name: hgcroc-configuration-client
Version: 1.2.3
Summary: Client for communication with HGCROC-tools' ROC                 configuration server
Home-page: https://gitlab.cern.ch/albecker/hgcroc-tools.git
Author: Alex Becker, Jonathan Trieloff
Author-email: j.trieloff@cern.ch
License: MIT
Classifier: License :: OSI Approved :: MIT License
Classifier: Programming Language :: Python :: 3
Classifier: Programming Language :: Python :: 3.7
Requires-Dist: attrs
Requires-Dist: Babel
Requires-Dist: certifi
Requires-Dist: charset-normalizer
Requires-Dist: contextlib2
Requires-Dist: hgcal-utilities
Requires-Dist: idna
Requires-Dist: iniconfig
Requires-Dist: Jinja2
Requires-Dist: MarkupSafe
Requires-Dist: numpy
Requires-Dist: packaging
Requires-Dist: pandas
Requires-Dist: pathlib2
Requires-Dist: pluggy
Requires-Dist: py
Requires-Dist: Pygments
Requires-Dist: pyparsing
Requires-Dist: pytest
Requires-Dist: python-dateutil
Requires-Dist: pytz
Requires-Dist: PyYAML
Requires-Dist: pyzmq
Requires-Dist: requests
Requires-Dist: schema
Requires-Dist: six
Requires-Dist: snowballstemmer
Requires-Dist: tomli
Requires-Dist: urllib3
Requires-Dist: zmq
